{"name":"test001","id":"com.lc.df.studentapp.studentinfo.StudentCRUDTest:test001","testCaseName":"com.lc.df.studentapp.studentinfo.StudentCRUDTest","testSteps":[{"number":1,"description":"POST http://localhost:8085/student\r\r","duration":3,"startTime":"2020-05-20T17:15:29.441+01:00[Europe/London]","result":"SUCCESS","restQuery":{"method":"POST","path":"http://localhost:8085/student\r\r","content":"{\n    \"firstName\": \"Shraddha82559\",\n    \"lastName\": \"Maheta49748\",\n    \"email\": \"smaheta14531@gmail.com\",\n    \"programme\": \"Automation Tester\",\n    \"courses\": [\n        \"Manual\",\n        \"Java\",\n        \"Selenium\"\n    ]\n}\r","contentType":"application/json","requestHeaders":"Accept\u003d*/*\r\n\t\t\t\tContent-Type\u003dapplication/json; charset\u003dUTF-8\r\r","requestCookies":"\r\r","responseHeaders":"Location: http://localhost:8085/student/104\nContent-Type: application/json;charset\u003dUTF-8\nTransfer-Encoding: chunked\nDate: Wed, 20 May 2020 16:15:29 GMT\r","responseCookies":"\r","responseBody":"{\n    \"msg\": \"Student added\"\n}","statusCode":201},"precondition":false}],"userStory":{"id":"com.lc.df.studentapp.studentinfo.StudentCRUDTest","storyName":"Student CRUD test","storyClassName":"com.lc.df.studentapp.studentinfo.StudentCRUDTest","path":"com.lc.df.studentapp.studentinfo","type":"story"},"featureTag":{"name":"Studentinfo/Student CRUD test","type":"story"},"title":"This test will create a new student record","tags":[{"name":"Studentinfo/Student CRUD test","type":"story"}],"startTime":"2020-05-20T17:15:22.980+01:00[Europe/London]","duration":6540,"projectKey":"","manual":false,"testSource":"JUnit","result":"SUCCESS"}